Metadata-Version: 2.4
Name: llama-index-llms-asi
Version: 0.2.1
Summary: llama-index llms asi integration
Author-email: "Fetch.ai Inc." <info@fetch.ai>
License-Expression: MIT
License-File: LICENSE
Requires-Python: <4.0,>=3.9
Requires-Dist: llama-index-core<0.15,>=0.13.0
Requires-Dist: llama-index-llms-openai-like<0.6,>=0.5.0
Requires-Dist: requests>=2.31.0
